[
  {
    "scheme": "https://",
    "land_domain": "e66qfkns.com",
    "ext": ".app",
    "status": "200"
  },
  {
    "scheme": "https://",
    "land_domain": "e66qfkns.com",
    "ext": ".html",
    "status": "200"
  },
  {
    "scheme": "https://",
    "land_domain": "e66qfkns.com",
    "ext": ".html",
    "status": "200"
  },
    {
    "scheme": "https://",
    "land_domain": "e66qfkns.com",
    "ext": ".app",
    "status": "200"
  },
  {
    "scheme": "https://",
    "land_domain": "e66qfkns.com",
    "ext": ".html",
    "status": "200"
  },
  {
    "scheme": "https://",
    "land_domain": "e66qfkns.com",
    "ext": ".html",
    "status": "200"
  }
]
